<root>
<menu_item type="default" category="Appetizers" price=" 7.75" descript="" itemname="Fried Calamari"></menu_item>
<menu_item type="default" category="Appetizers" price=" 7.75" descript="" itemname="Chicken Fingers"></menu_item>
<menu_item type="default" category="Appetizers" price=" 7.75" descript="" itemname="Buffalo Chicken Wings"></menu_item>
<menu_item type="default" category="Appetizers" price=" 7.75" descript="" itemname="Fried Wontons"></menu_item>
<menu_item type="default" category="Appetizers" price=" 7.75" descript="" itemname="Stuffed Mushrooms"></menu_item>
<menu_item type="default" category="Appetizers" price=" 7.00" descript="" itemname="Mozzarella Sticks"></menu_item>
<menu_item type="default" category="Appetizers" price=" 7.75" descript="" itemname="Stuffed Potato Skins"></menu_item>
<menu_item type="default" category="Appetizers" price=" 7.75" descript="" itemname="Jalapeno Poppers"></menu_item>
<menu_item type="default" category="Appetizers" price=" 4.50" descript="" itemname="Crispy Onions"></menu_item>
<menu_item type="default" category="Appetizers" price=" 3.75" descript="" itemname="French Fries"></menu_item>
<menu_item type="default" category="Appetizers" price=" 5.20" descript="" itemname="Cheese Fries"></menu_item>
<menu_item type="default" category="Soups" price=" 4.50" descript="" itemname="French Onion Soup"></menu_item>
<menu_item type="default" category="Soups" price="bowl 4.00" descript="" itemname="Soup Of The Day"></menu_item>
<menu_item type="default" category="Salads" price=" 5.99" descript="" itemname="House Salad"></menu_item>
<menu_item type="default" category="Salads" price=" 9.75" descript="" itemname="Spinach Salad"></menu_item>
<menu_item type="default" category="Salads" price=" 9.75" descript="" itemname="Tuna Salad"></menu_item>
<menu_item type="default" category="Salads" price=" 9.75" descript="" itemname="Caesar Salad"></menu_item>
<menu_item type="default" category="Salads" price=" 9.75" descript="" itemname="Nicoise Salad"></menu_item>
<menu_item type="default" category="Salads" price=" 9.75" descript="" itemname="Chef Salad"></menu_item>
<menu_item type="default" category="Salads" price=" 9.75" descript="" itemname="Oriental Salad"></menu_item>
<menu_item type="default" category="Sandwiches" price=" 9.65" descript="" itemname="French Dip"></menu_item>
<menu_item type="default" category="Sandwiches" price=" 8.95" descript="" itemname="Metro Special"></menu_item>
<menu_item type="default" category="Sandwiches" price=" 9.65" descript="" itemname="B.B.Q. Chicken Breast"></menu_item>
<menu_item type="default" category="Sandwiches" price=" 9.65" descript="" itemname="Turkey Club"></menu_item>
<menu_item type="default" category="Sandwiches" price=" 8.95" descript="" itemname="Turkey Breast"></menu_item>
<menu_item type="default" category="Sandwiches" price=" 8.95" descript="" itemname="Virginia Ham &amp;amp; Swiss Cheese"></menu_item>
<menu_item type="default" category="Sandwiches" price=" 8.95" descript="" itemname="Tuna Melt"></menu_item>
<menu_item type="default" category="Famous 9 Ounce Burger" price=" 8.99" descript="served on a toasted roll with lettuce, tomato and fresh fries" itemname="Juicy Burger Cooked Or Order"></menu_item>
<menu_item type="default" category="Entrees" price=" 8.50" descript="" itemname="Omelets"></menu_item>
<menu_item type="default" category="Entrees" price=" 12.95" descript="grilled chicken" itemname="Caesar Salad"></menu_item>
<menu_item type="default" category="Entrees" price=" 13.95" descript="" itemname="grilled shrimp"></menu_item>
<menu_item type="default" category="Entrees" price=" 7.95" descript="" itemname="Quiche And Salad"></menu_item>
<menu_item type="default" category="Entrees" price=" 11.95" descript="" itemname="Pasta Of The Day"></menu_item>
<menu_item type="default" category="Entrees" price=" " descript="" itemname="Catch Of The Day"></menu_item>
<menu_item type="default" category="Entrees" price=" 12.50" descript="" itemname="Boiled Or Blackened Salmon"></menu_item>
<menu_item type="default" category="Entrees" price=" 13.95" descript="" itemname="Shrimp Scampi"></menu_item>
<menu_item type="default" category="Entrees" price=" 11.95" descript="" itemname="Chicken Breast"></menu_item>
<menu_item type="default" category="Entrees" price=" 11.95" descript="" itemname="Lemon Chicken"></menu_item>
<menu_item type="default" category="Entrees" price=" 13.50" descript="" itemname="Stuffed Pork Chops"></menu_item>
<menu_item type="default" category="Entrees" price=" 10.95" descript="" itemname="Shepard's Pie"></menu_item>
<menu_item type="default" category="Entrees" price=" 13.95" descript="" itemname="Sliced Steak"></menu_item>
<menu_item type="default" category="Entrees" price=" 18.95" descript="" itemname="14 Oz. Shell Steak"></menu_item>
<menu_item type="default" category="Add Some Extras $9.50" price=" " descript="" itemname="Sauteed Onions"></menu_item>
<menu_item type="default" category="Add Some Extras $9.50" price=" " descript="" itemname="Crispy Bacon"></menu_item>
<menu_item type="default" category="Add Some Extras $9.50" price=" " descript="" itemname="Sauteed Mushrooms"></menu_item>
<menu_item type="default" category="Add Some Extras $9.50" price=" " descript="" itemname="Swiss Cheese"></menu_item>
<menu_item type="default" category="Add Some Extras $9.50" price=" " descript="" itemname="American Cheese"></menu_item>
<menu_item type="default" category="Add Some Extras $9.50" price=" " descript="" itemname="Mozzarella"></menu_item>
<menu_item type="default" category="Add Some Extras $9.50" price=" " descript="" itemname="Cheddar"></menu_item>
</root>
